pywasher/__init__.py
pywasher/app.py
pywasher-1.3.1.dist-info/LICENSE
pywasher-1.3.1.dist-info/METADATA
pywasher-1.3.1.dist-info/WHEEL
pywasher-1.3.1.dist-info/top_level.txt
pywasher-1.3.1.dist-info/RECORD
