Metadata-Version: 2.1
Name: pywasher
Version: 1.3.1
Summary: pywasher
Home-page: https://github.com/jeroenclappform/pywasher
Author: StanBekker
Author-email: s.bekker@clappform.com
License: MIT
Download-URL: https://github.com/jeroenclappform/pywasher/archive/1.3.1.tar.gz
Keywords: dataframe cleaner
Platform: UNKNOWN
Classifier: Development Status :: 5 - Production/Stable
Classifier: License :: OSI Approved :: MIT License
Classifier: Programming Language :: Python :: 3
Classifier: Operating System :: OS Independent
Requires-Dist: pandas
